{
 "_meta": {
  "collecte": "13 juin 2026 (line shopping multi-sources : Oddspedia/1xbet, bet365, FanDuel, BetOnline/BetNow, Oddschecker, Kalshi)",
  "note": "est=true : cote partiellement estimee. o25/btts majoritairement estimes : info seulement, pas de value dessus sauf si precise.",
  "cartons_corners": "cards/corners ajoutes (est=true) pour 25 (Suisse-Bosnie) et 16 (France-Senegal) en demo ; l'agent cotes mettra de vraies lignes."
 },
 "2": {
  "match": "Canada-Bosnia",
  "h": 1.8,
  "d": 3.8,
  "a": 4.2,
  "o25": 2.1,
  "btts": 2.15,
  "est": false,
  "_note": "joue 12/06, score 1-1 - cloture non trouvee"
 },
 "3": {
  "match": "USA-Paraguay",
  "h": 2.0,
  "d": 3.5,
  "a": 4.1,
  "o25": 2.2,
  "btts": 2.1,
  "est": false,
  "_note": "joue 12/06, score 4-1 - cloture non trouvee"
 },
 "4": {
  "match": "Qatar-Switzerland",
  "h": 15.5,
  "d": 7.0,
  "a": 1.26,
  "o25": 2.1,
  "btts": 2.2,
  "est": false,
  "sources": [
   {
    "h": 15.5,
    "d": 7.0,
    "a": 1.26,
    "w": 0.1
   },
   {
    "h": 13.0,
    "d": 7.0,
    "a": 1.2,
    "w": 0.1
   }
  ]
 },
 "5": {
  "match": "Brazil-Morocco",
  "h": 1.69,
  "d": 4.0,
  "a": 6.1,
  "o25": 2.0,
  "btts": 2.04,
  "est": false,
  "sources": [
   {
    "h": 1.667,
    "d": 3.7,
    "a": 5.6,
    "w": 0.15
   },
   {
    "h": 1.571,
    "d": 4.0,
    "a": 5.25,
    "w": 0.15
   },
   {
    "h": 1.69,
    "d": 3.9,
    "a": 5.5,
    "w": 0.1
   }
  ]
 },
 "6": {
  "match": "Haiti-Scotland",
  "h": 7.5,
  "d": 4.8,
  "a": 1.615,
  "o25": 2.05,
  "btts": 2.1,
  "est": false
 },
 "7": {
  "match": "Australia-Turkey",
  "h": 5.5,
  "d": 3.9,
  "a": 1.75,
  "o25": 1.95,
  "btts": 1.85,
  "est": false
 },
 "8": {
  "match": "Germany-Curacao",
  "h": 1.05,
  "d": 22.0,
  "a": 55.0,
  "o25": 1.3,
  "btts": 3.0,
  "est": false,
  "sources": [
   {
    "h": 1.02,
    "d": 22.0,
    "a": 40.0,
    "w": 0.15
   },
   {
    "h": 1.03,
    "d": 19.0,
    "a": 34.0,
    "w": 0.15
   },
   {
    "h": 1.05,
    "d": 16.5,
    "a": 55.0,
    "w": 0.1
   }
  ]
 },
 "9": {
  "match": "Netherlands-Japan",
  "h": 2.26,
  "d": 2.88,
  "a": 3.93,
  "o25": 2.24,
  "btts": 1.85,
  "est": false,
  "api": "the-odds-api",
  "o25_under": 1.9,
  "n_books": 1
 },
 "10": {
  "match": "Ivory Coast-Ecuador",
  "h": 3.38,
  "d": 2.91,
  "a": 2.65,
  "o25": 3.05,
  "btts": 2.05,
  "est": false,
  "api": "the-odds-api",
  "o25_under": 1.41,
  "n_books": 2
 },
 "11": {
  "match": "Sweden-Tunisia",
  "h": 1.96,
  "d": 3.46,
  "a": 4.5,
  "o25": 2.17,
  "btts": 2.1,
  "est": false,
  "_note": "cotes bet365 trouvees (Suede +500/Tunisie +1000) incoherentes avec un favori Suede - rejetees, conservation des cotes du 12/06",
  "api": "the-odds-api",
  "o25_under": 1.7,
  "n_books": 2
 },
 "12": {
  "match": "Spain-Cape Verde",
  "h": 1.11,
  "d": 11.78,
  "a": 26.0,
  "o25": 1.36,
  "btts": 2.625,
  "est": false,
  "api": "the-odds-api",
  "o25_under": 3.2,
  "n_books": 2
 },
 "13": {
  "match": "Belgium-Egypt",
  "h": 1.67,
  "d": 4.01,
  "a": 5.75,
  "o25": 2.04,
  "btts": 2.0,
  "est": false,
  "api": "the-odds-api",
  "o25_under": 1.86,
  "n_books": 2
 },
 "14": {
  "match": "Saudi Arabia-Uruguay",
  "h": 7.7,
  "d": 4.32,
  "a": 1.5,
  "o25": 2.06,
  "btts": 2.15,
  "est": false,
  "api": "the-odds-api",
  "n_books": 2,
  "o25_under": 1.78
 },
 "15": {
  "match": "Iran-New Zealand",
  "h": 1.96,
  "d": 3.4,
  "a": 4.51,
  "o25": 2.42,
  "btts": 2.4,
  "est": false,
  "api": "the-odds-api",
  "n_books": 2,
  "o25_under": 1.58
 },
 "16": {
  "match": "France-Senegal",
  "h": 1.5,
  "d": 4.49,
  "a": 7.31,
  "o25": 1.98,
  "btts": 2.05,
  "est": false,
  "cards": {
   "line": 4.5,
   "over": 1.85,
   "under": 1.95,
   "est": true
  },
  "corners": {
   "line": 9.5,
   "over": 1.9,
   "under": 1.9,
   "est": true
  },
  "sources": [
   {
    "h": 1.44,
    "d": 4.5,
    "a": 7.0,
    "w": 0.15
   },
   {
    "h": 1.47,
    "d": 4.6,
    "a": 7.8,
    "w": 0.15
   },
   {
    "h": 1.45,
    "d": 4.4,
    "a": 6.5,
    "w": 0.1
   }
  ],
  "api": "the-odds-api",
  "n_books": 2,
  "o25_under": 1.91
 },
 "17": {
  "match": "Iraq-Norway",
  "h": 17.5,
  "d": 7.53,
  "a": 1.2,
  "o25": 1.58,
  "btts": 2.4,
  "est": false,
  "api": "the-odds-api",
  "n_books": 2,
  "o25_under": 2.42
 },
 "18": {
  "match": "Argentina-Algeria",
  "h": 1.42,
  "d": 4.57,
  "a": 9.6,
  "o25": 2.01,
  "btts": 2.2,
  "est": false,
  "api": "the-odds-api",
  "n_books": 2,
  "o25_under": 1.88
 },
 "19": {
  "match": "Austria-Jordan",
  "h": 1.35,
  "d": 5.45,
  "a": 9.65,
  "o25": 1.69,
  "btts": 2.45,
  "est": false,
  "api": "the-odds-api",
  "n_books": 2,
  "o25_under": 2.2
 },
 "20": {
  "match": "Portugal-DR Congo",
  "h": 1.33,
  "d": 5.75,
  "a": 11.22,
  "o25": 1.73,
  "btts": 2.3,
  "est": false,
  "api": "the-odds-api",
  "n_books": 2,
  "o25_under": 2.14
 },
 "21": {
  "match": "England-Croatia",
  "h": 1.75,
  "d": 3.9,
  "a": 5.07,
  "o25": 2.15,
  "btts": 1.95,
  "est": false,
  "api": "the-odds-api",
  "n_books": 2,
  "o25_under": 1.72
 },
 "22": {
  "match": "Ghana-Panama",
  "h": 2.2,
  "d": 3.53,
  "a": 3.51,
  "o25": 2.27,
  "btts": 2.2,
  "est": false,
  "api": "the-odds-api",
  "n_books": 2,
  "o25_under": 1.65
 },
 "23": {
  "match": "Uzbekistan-Colombia",
  "h": 9.65,
  "d": 4.78,
  "a": 1.4,
  "o25": 1.97,
  "btts": 2.0,
  "est": false,
  "api": "the-odds-api",
  "n_books": 2,
  "o25_under": 1.92
 },
 "24": {
  "match": "Czechia-South Africa",
  "h": 1.81,
  "d": 3.9,
  "a": 4.62,
  "o25": 2.08,
  "btts": 2.25,
  "est": false,
  "api": "the-odds-api",
  "n_books": 2,
  "o25_under": 1.77
 },
 "25": {
  "match": "Switzerland-Bosnia",
  "h": 1.61,
  "d": 4.19,
  "a": 6.25,
  "o25": 2.09,
  "btts": 2.2,
  "est": false,
  "cards": {
   "line": 4.5,
   "over": 1.85,
   "under": 1.95,
   "est": true
  },
  "corners": {
   "line": 9.5,
   "over": 1.9,
   "under": 1.9,
   "est": true
  },
  "api": "the-odds-api",
  "n_books": 2,
  "o25_under": 1.75
 },
 "26": {
  "match": "Canada-Qatar",
  "h": 1.3,
  "d": 5.8,
  "a": 12.4,
  "o25": 1.8,
  "btts": 2.6,
  "est": false,
  "api": "the-odds-api",
  "n_books": 2,
  "o25_under": 2.04
 },
 "27": {
  "match": "Mexico-South Korea",
  "h": 2.03,
  "d": 3.42,
  "a": 4.27,
  "o25": 2.4,
  "btts": 2.05,
  "est": false,
  "api": "the-odds-api",
  "n_books": 2,
  "o25_under": 1.59
 },
 "29": {
  "est": false,
  "api": "the-odds-api",
  "n_books": 2,
  "h": 1.62,
  "a": 5.68,
  "d": 4.36,
  "o25": 2.0,
  "o25_under": 1.88
 },
 "28": {
  "est": false,
  "api": "the-odds-api",
  "n_books": 2,
  "h": 5.12,
  "a": 1.81,
  "d": 3.68,
  "o25": 2.22,
  "o25_under": 1.68
 },
 "30": {
  "est": false,
  "api": "the-odds-api",
  "n_books": 2,
  "h": 1.12,
  "a": 25.0,
  "d": 11.85
 },
 "31": {
  "est": false,
  "api": "the-odds-api",
  "n_books": 41,
  "h": 2.1,
  "a": 4.0,
  "d": 3.5,
  "o25": 2.24,
  "o25_under": 1.8
 },
 "32": {
  "est": false,
  "api": "the-odds-api",
  "n_books": 41,
  "h": 4.9,
  "a": 8.7,
  "d": 4.2,
  "o25": 1.67,
  "o25_under": 2.36
 },
 "33": {
  "est": false,
  "api": "the-odds-api",
  "n_books": 42,
  "h": 4.0,
  "a": 10.75,
  "d": 4.8,
  "o25": 1.64,
  "o25_under": 2.52
 },
 "34": {
  "est": false,
  "api": "the-odds-api",
  "n_books": 42,
  "h": 3.52,
  "a": 28.0,
  "d": 10.5,
  "o25": 1.55,
  "o25_under": 2.5
 },
 "35": {
  "est": false,
  "api": "the-odds-api",
  "n_books": 42,
  "h": 9.4,
  "a": 4.6,
  "d": 4.1,
  "o25": 2.14,
  "o25_under": 1.78
 },
 "36": {
  "est": false,
  "api": "the-odds-api",
  "n_books": 42,
  "h": 3.42,
  "a": 33.0,
  "d": 13.0,
  "o25": 1.4,
  "o25_under": 3.25
 },
 "37": {
  "est": false,
  "api": "the-odds-api",
  "n_books": 42,
  "h": 4.4,
  "a": 12.0,
  "d": 5.0,
  "o25": 1.85,
  "o25_under": 2.16,
  "match": "Belgium-Iran",
  "btts": 2.1
 },
 "38": {
  "est": false,
  "api": "the-odds-api",
  "n_books": 42,
  "h": 4.55,
  "a": 12.75,
  "d": 4.4,
  "o25": 2.32,
  "o25_under": 1.67
 },
 "39": {
  "est": false,
  "api": "the-odds-api",
  "n_books": 42,
  "h": 9.8,
  "a": 4.9,
  "d": 4.2,
  "o25": 2.14,
  "o25_under": 1.84
 },
 "40": {
  "est": false,
  "api": "the-odds-api",
  "n_books": 41,
  "h": 1.53,
  "a": 8.8,
  "d": 4.6,
  "o25": 1.99,
  "o25_under": 2.0
 },
 "41": {
  "est": false,
  "api": "the-odds-api",
  "n_books": 41,
  "h": 1.13,
  "a": 42.0,
  "d": 15.0,
  "o25": 1.35,
  "o25_under": 3.5
 },
 "42": {
  "est": false,
  "api": "the-odds-api",
  "n_books": 41,
  "h": 2.28,
  "a": 3.5,
  "d": 3.6,
  "o25": 1.95,
  "o25_under": 2.04
 },
 "43": {
  "est": false,
  "api": "the-odds-api",
  "n_books": 41,
  "h": 7.07,
  "a": 1.6,
  "d": 4.6,
  "o25": 2.02,
  "o25_under": 1.96
 },
 "44": {
  "est": false,
  "api": "the-odds-api",
  "n_books": 41,
  "h": 1.23,
  "a": 20.0,
  "d": 7.8,
  "o25": 1.65,
  "o25_under": 2.45
 },
 "45": {
  "est": false,
  "api": "the-odds-api",
  "n_books": 41,
  "h": 1.25,
  "a": 17.5,
  "d": 7.2,
  "o25": 1.7,
  "o25_under": 2.3
 },
 "46": {
  "est": false,
  "api": "the-odds-api",
  "n_books": 41,
  "h": 7.4,
  "a": 1.58,
  "d": 4.3,
  "o25": 1.95,
  "o25_under": 2.1
 },
 "47": {
  "est": false,
  "api": "the-odds-api",
  "n_books": 39,
  "h": 1.55,
  "a": 7.8,
  "d": 4.4,
  "o25": 2.28,
  "o25_under": 1.69
 },
 "49": {
  "est": false,
  "api": "the-odds-api",
  "n_books": 41,
  "h": 1.48,
  "a": 7.6,
  "d": 5.2,
  "o25": 1.68,
  "o25_under": 2.28
 },
 "48": {
  "est": false,
  "api": "the-odds-api",
  "n_books": 40,
  "h": 2.6,
  "a": 3.39,
  "d": 3.2,
  "o25": 2.2,
  "o25_under": 1.77
 },
 "50": {
  "est": false,
  "api": "the-odds-api",
  "n_books": 40,
  "h": 9.7,
  "a": 1.42,
  "d": 5.6,
  "o25": 1.92,
  "o25_under": 2.02
 },
 "51": {
  "est": false,
  "api": "the-odds-api",
  "n_books": 40,
  "h": 1.23,
  "a": 19.5,
  "d": 7.8,
  "o25": 1.62,
  "o25_under": 2.43
 },
 "52": {
  "est": false,
  "api": "the-odds-api",
  "n_books": 40,
  "h": 4.1,
  "a": 2.01,
  "d": 4.2,
  "o25": 2.12,
  "o25_under": 1.83
 },
 "53": {
  "est": false,
  "api": "the-odds-api",
  "n_books": 40,
  "h": 6.0,
  "a": 1.69,
  "d": 4.05,
  "o25": 2.1,
  "o25_under": 1.8
 },
 "55": {
  "est": false,
  "api": "the-odds-api",
  "n_books": 40,
  "h": 25.0,
  "a": 1.18,
  "d": 9.4,
  "o25": 1.52,
  "o25_under": 2.7
 },
 "54": {
  "est": false,
  "api": "the-odds-api",
  "n_books": 40,
  "h": 3.77,
  "a": 2.0,
  "d": 4.2,
  "o25": 1.85,
  "o25_under": 2.06
 },
 "56": {
  "est": false,
  "api": "the-odds-api",
  "n_books": 40,
  "h": 2.02,
  "a": 4.6,
  "d": 3.6,
  "o25": 1.85,
  "o25_under": 2.12
 },
 "57": {
  "est": false,
  "api": "the-odds-api",
  "n_books": 39,
  "h": 30.03,
  "a": 1.16,
  "d": 10.0,
  "o25": 1.48,
  "o25_under": 2.75
 },
 "59": {
  "est": false,
  "api": "the-odds-api",
  "n_books": 40,
  "h": 3.04,
  "a": 4.25,
  "d": 2.38,
  "o25": 2.92,
  "o25_under": 1.43
 },
 "58": {
  "est": false,
  "api": "the-odds-api",
  "n_books": 40,
  "h": 3.8,
  "a": 2.06,
  "d": 4.35,
  "o25": 1.76,
  "o25_under": 2.18
 },
 "60": {
  "est": false,
  "api": "the-odds-api",
  "n_books": 37,
  "h": 4.75,
  "a": 1.82,
  "d": 4.1,
  "o25": 1.82,
  "o25_under": 2.07
 },
 "61": {
  "est": false,
  "api": "the-odds-api",
  "n_books": 37,
  "h": 1.37,
  "a": 12.1,
  "d": 5.9,
  "o25": 1.88,
  "o25_under": 2.1
 },
 "62": {
  "est": false,
  "api": "the-odds-api",
  "n_books": 36,
  "h": 2.48,
  "a": 3.05,
  "d": 3.66,
  "o25": 2.08,
  "o25_under": 1.9
 },
 "63": {
  "est": false,
  "api": "the-odds-api",
  "n_books": 36,
  "h": 8.0,
  "a": 1.54,
  "d": 4.51,
  "o25": 1.87,
  "o25_under": 2.07
 },
 "65": {
  "est": false,
  "api": "the-odds-api",
  "n_books": 35,
  "h": 16.0,
  "a": 1.24,
  "d": 7.2,
  "o25": 1.65,
  "o25_under": 2.43
 },
 "64": {
  "est": false,
  "api": "the-odds-api",
  "n_books": 36,
  "h": 2.52,
  "a": 4.0,
  "d": 2.88,
  "o25": 2.6,
  "o25_under": 1.46
 },
 "67": {
  "est": false,
  "api": "the-odds-api",
  "n_books": 35,
  "h": 1.68,
  "a": 6.6,
  "d": 4.0,
  "o25": 2.14,
  "o25_under": 1.83
 },
 "66": {
  "est": false,
  "api": "the-odds-api",
  "n_books": 35,
  "h": 13.0,
  "a": 1.26,
  "d": 7.8,
  "o25": 1.62,
  "o25_under": 2.38
 },
 "68": {
  "est": false,
  "api": "the-odds-api",
  "n_books": 35,
  "h": 3.8,
  "a": 2.12,
  "d": 3.7,
  "o25": 2.14,
  "o25_under": 1.81
 },
 "69": {
  "est": false,
  "api": "the-odds-api",
  "n_books": 35,
  "h": 2.14,
  "a": 3.6,
  "d": 3.85,
  "o25": 2.18,
  "o25_under": 1.79
 },
 "70": {
  "est": false,
  "api": "the-odds-api",
  "n_books": 35,
  "h": 3.25,
  "a": 2.66,
  "d": 3.15,
  "o25": 2.22,
  "o25_under": 1.75
 },
 "71": {
  "est": false,
  "api": "the-odds-api",
  "n_books": 35,
  "h": 16.0,
  "a": 1.23,
  "d": 8.0,
  "o25": 1.57,
  "o25_under": 2.43
 }
}